gnistai/__init__.py
gnistai-0.0.2.dist-info/METADATA
gnistai-0.0.2.dist-info/WHEEL
gnistai-0.0.2.dist-info/licenses/LICENSE
gnistai-0.0.2.dist-info/RECORD
