Metadata-Version: 2.4
Name: gnistai
Version: 0.0.2
Summary: The official Python library for the GnistAI API
Project-URL: Homepage, https://gnist.ai/api/docs
Project-URL: Repository, https://github.com/gnistai/gnistai-python
Project-URL: Issues, https://github.com/gnistai/gnistai-python/issues
Author-email: GnistAI <office@gnist.ai>
License: Apache-2.0
License-File: LICENSE
Classifier: License :: OSI Approved :: Apache Software License
Classifier: Operating System :: MacOS
Classifier: Operating System :: Microsoft :: Windows
Classifier: Operating System :: OS Independent
Classifier: Operating System :: POSIX
Classifier: Operating System :: POSIX :: Linux
Classifier: Programming Language :: Python :: 3.11
Classifier: Programming Language :: Python :: 3.12
Classifier: Programming Language :: Python :: 3.13
Classifier: Topic :: Software Development :: Libraries :: Python Modules
Classifier: Typing :: Typed
Requires-Python: >=3.11
Requires-Dist: requests<3,>=2.32.3
